min_llm_agent/__init__.py
min_llm_agent/min_llm_agent.py
utils/Util_import.py
utils/__init__.py
MinimalLLMAgent-0.1.5.dist-info/LICENSE
MinimalLLMAgent-0.1.5.dist-info/METADATA
MinimalLLMAgent-0.1.5.dist-info/WHEEL
MinimalLLMAgent-0.1.5.dist-info/top_level.txt
MinimalLLMAgent-0.1.5.dist-info/RECORD
