Metadata-Version: 2.1
Name: MinimalLLMAgent
Version: 0.1.5
Summary: A minimal LLM agent with memory management.
Home-page: https://github.com/YueLin301/min_llm_agent
Author: Yue Lin
Author-email: linyue3h1@gmail.com
Classifier: Programming Language :: Python :: 3
Classifier: License :: OSI Approved :: MIT License
Classifier: Operating System :: OS Independent
License-File: LICENSE
Requires-Dist: LyPythonToolbox==0.1.4
Requires-Dist: openai==2.2.0
